{
    "title": "点击 - 静态检测",
    "group": {
        "key": "auto",
        "label": "点击器"
    },
    "info": [
        "1.检测窗口内容是否静止;在设定的时间间隔前后对窗口截图,对比RGB三通道的ssim(结构相似度),返回最低得分;首次检测到静态后等待3倍间隔时间再次检测,若仍为静态则发送右下角windows通知",
        "2.目标窗口不能最小化,不能改大小(尺寸判断懒得做了),还有一些参数也懒得放到前端了,通通默认"
    ],
    "require": [
        {
            "type": "input",
            "data": {
                "key": "path_cash",
                "label": "缓存路径",
                "value": "D:\\s-linux\\project\\test_file\\cash",
                "annotation": [
                    "用以保存临时截图文件"
                ]
            }
        },
        {
            "type": "input",
            "data": {
                "key": "win_name",
                "label": "目标窗口名",
                "value": "碧蓝航线",
                "annotation": [
                    "支持字符串匹配,输入关键字即可",
                    "匹配到重复窗口时使用第一个"
                ]
            }
        },
        {
            "type": "input",
            "data": {
                "key": "interval_time",
                "label": "检测间隔",
                "value": "3",
                "annotation": [
                    "in型,单位秒"
                ]
            }
        },
        {
            "type": "button",
            "data": {
                "key": "open_cash",
                "label": "打开cash文件夹",
                "button": "打开",
                "annotation": [
                    "打开cash文件夹",
                    "看看到底一样不一样"
                ]
            }
        }
    ]
}